pdftex/__init__.py
pdftex/pdftex.py
pdftex-1.0.0.dist-info/LICENSE
pdftex-1.0.0.dist-info/METADATA
pdftex-1.0.0.dist-info/WHEEL
pdftex-1.0.0.dist-info/top_level.txt
pdftex-1.0.0.dist-info/zip-safe
pdftex-1.0.0.dist-info/RECORD
