Metadata-Version: 2.1
Name: pdftex
Version: 1.0.0
Summary: pdftex backend for matplotlib
Home-page: https://github.com/fvarno/PDFTex
Author: Farshid Varno
Author-email: fr.varno@gmail.com
License: GNU General Public License v3.0
Download-URL: https://github.com/fvarno/PDFTex.git
Platform: UNKNOWN
Classifier: Development Status :: 2 - Pre-Alpha 
Classifier: Environment :: Console
Classifier: Intended Audience :: Science/Research
Classifier: Intended Audience :: Education
Classifier: License :: OSI Approved :: GNU General Public License v3 (GPLv3)
Classifier: Operating System :: POSIX :: Linux
Classifier: Programming Language :: Python
Classifier: Topic :: Scientific/Engineering :: Visualization
Classifier: Topic :: Text Processing :: Markup :: LaTeX
Classifier: Framework :: Matplotlib
Requires-Dist: matplotlib
Requires-Dist: pillow
